{
  "lastmod":  "2018-05-07T12:01:04.884Z",
  "releases": [
    {
      "type": "Alpha",
      "version":  "180506",
      "files": [
        {
          "type": "7-Zip",
          "urls": [
            "https://github.com/Maximus5/ConEmu/releases/download/v18.05.06/ConEmuPack.180506.7z",
            "http://downloads.sf.net/project/conemu/Preview/ConEmuPack.180506.7z?use_mirror=autoselect"
          ],
          "size":   4465717,
          "crc32": "5F159CDE",
          "md5":   "52bb17db47b66d55f228aba8d4819aa1",
          "description": "Alpha, Portable (32-bit, 64-bit)"
        },
        {
          "type": "Installer",
          "urls": [
            "https://github.com/Maximus5/ConEmu/releases/download/v18.05.06/ConEmuSetup.180506.exe",
            "http://downloads.sf.net/project/conemu/Preview/ConEmuSetup.180506.exe?use_mirror=autoselect"
          ],
          "size":   6743616,
          "crc32": "2AA3E922",
          "md5":   "ca4d340d4e5ec192685d263580c556a3",
          "description": "Alpha, Installer (32-bit, 64-bit)"
        },
        {
          "type": "PortableApps",
          "urls": [
            "https://github.com/Maximus5/ConEmu/releases/download/v18.05.06/ConEmu_180506_English.paf.exe",
            "http://downloads.sf.net/project/conemu/PortableApps/ConEmu_180506_English.paf.exe?use_mirror=autoselect"
          ],
          "size":   4351424,
          "crc32": "EE7AC1DF",
          "md5":   "7c54ad3ef7702b2175e473303e253efb",
          "description": "Alpha, PortableApps.com"
        }
      ]
    },
    {
      "type": "Preview",
      "version":  "180506",
      "files": [
        {
          "type": "7-Zip",
          "urls": [
            "https://github.com/Maximus5/ConEmu/releases/download/v18.05.06/ConEmuPack.180506.7z",
            "http://downloads.sf.net/project/conemu/Preview/ConEmuPack.180506.7z?use_mirror=autoselect"
          ],
          "size":   4465717,
          "crc32": "5F159CDE",
          "md5":   "52bb17db47b66d55f228aba8d4819aa1",
          "description": "Preview, Portable (32-bit, 64-bit)"
        },
        {
          "type": "Installer",
          "urls": [
            "https://github.com/Maximus5/ConEmu/releases/download/v18.05.06/ConEmuSetup.180506.exe",
            "http://downloads.sf.net/project/conemu/Preview/ConEmuSetup.180506.exe?use_mirror=autoselect"
          ],
          "size":   6743616,
          "crc32": "2AA3E922",
          "md5":   "ca4d340d4e5ec192685d263580c556a3",
          "description": "Preview, Installer (32-bit, 64-bit)"
        },
        {
          "type": "PortableApps",
          "urls": [
            "https://github.com/Maximus5/ConEmu/releases/download/v18.05.06/ConEmu_180506_English.paf.exe",
            "http://downloads.sf.net/project/conemu/PortableApps/ConEmu_180506_English.paf.exe?use_mirror=autoselect"
          ],
          "size":   4351424,
          "crc32": "EE7AC1DF",
          "md5":   "7c54ad3ef7702b2175e473303e253efb",
          "description": "Preview, PortableApps.com"
        }
      ]
    },
    {
      "type": "Stable",
      "version":  "161206",
      "files": [
        {
          "type": "7-Zip",
          "urls": [
            "https://github.com/Maximus5/ConEmu/releases/download/v16.12.06/ConEmuPack.161206.7z",
            "http://downloads.sf.net/project/conemu/Stable/ConEmuPack.161206.7z?use_mirror=autoselect"
          ],
          "size":   2834155,
          "crc32": "9814CDE4",
          "md5":   "5d1da28d4f6dca12a2809f901eb25c04",
          "description": "Stable, Portable (32-bit, 64-bit)"
        },
        {
          "type": "Installer",
          "urls": [
            "https://github.com/Maximus5/ConEmu/releases/download/v16.12.06/ConEmuSetup.161206.exe",
            "http://downloads.sf.net/project/conemu/Stable/ConEmuSetup.161206.exe?use_mirror=autoselect"
          ],
          "size":   5487408,
          "crc32": "609D7B55",
          "md5":   "ad57900d0d5f2cc0d2564bcdfc997d1d",
          "description": "Stable, Installer (32-bit, 64-bit)"
        },
        {
          "type": "PortableApps",
          "urls": [
            "https://github.com/Maximus5/ConEmu/releases/download/v16.12.06/ConEmu_161206_English.paf.exe",
            "http://downloads.sf.net/project/conemu/PortableApps/ConEmu_161206_English.paf.exe?use_mirror=autoselect"
          ],
          "size":   2637896,
          "crc32": "23C6DEC1",
          "md5":   "8fcd1bf843b281e5e8e8438d10aea9db",
          "description": "Stable, PortableApps.com"
        }
      ]
    }
  ]
}